{
  "id": "676d5827b892",
  "title": "Apple spent $10 million on U.S. lobbying in 2025, up nearly 30% from 2024",
  "url": "https://9to5mac.com/2026/01/22/apple-spent-a-record-10-million-on-us-lobbying-in-2025/",
  "source": "9to5Mac",
  "published_at": "2026-01-22T21:59:43Z",
  "sector": "General",
  "sentiment": {
    "polarity": 1.0,
    "label": "positive"
  },
  "full_text": "Apple spent $10 million on U.S. lobbying in 2025, up nearly 30% from 2024. Apple\u2019s federal lobbying spending surged in 2025, reaching a record $10 million after a nearly 30% year-over-year increase. Here are the details. more\u2026. Apples federal lobbying spending surged in 2025, reaching a record $10 million after a nearly 30% year-over-year increase. Here are the details. Earlier today, Bloomberg reported on the overall incr\u2026 [+1883 chars]",
  "chunks": [
    "Apple spent $10 million on U.S. lobbying in 2025, up nearly 30% from 2024. Apple\u2019s federal lobbying spending surged in 2025, reaching a record $10 million after a nearly 30% year-over-year increase. Here are the details. more\u2026. Apples federal lobbying spending surged in 2025, reaching a record $10 million after a nearly 30% year-over-year increase. Here are the details. Earlier today, Bloomberg reported on the overall incr\u2026 [+1883 chars]"
  ],
  "num_chunks": 1,
  "processed_at": "2026-02-07T11:42:03.600423"
}