{
  "id": "f9bb56702b56",
  "title": "America's K-shaped economy has turned restaurant winners and losers upside down",
  "url": "https://www.businessinsider.com/america-k-shaped-economy-breaking-fast-food-playbook-2026-2",
  "source": "Business Insider",
  "published_at": "2026-02-02T09:14:02Z",
  "sector": "General",
  "sentiment": {
    "polarity": -1.0,
    "label": "negative"
  },
  "full_text": "America's K-shaped economy has turned restaurant winners and losers upside down. Usually, fast-food consumption is a reliable recession indicator, but in a K-shaped economy, the old playbook has broken down, analysts say.. Clark stays away from foods made with refined white flour, and lots of added sugar.monticelllo/Getty Images <ul><li>Fast food's recession playbook is breaking as deals fail to lure pressured consume\u2026 [+5286 chars]",
  "chunks": [
    "America's K-shaped economy has turned restaurant winners and losers upside down. Usually, fast-food consumption is a reliable recession indicator, but in a K-shaped economy, the old playbook has broken down, analysts say.. Clark stays away from foods made with refined white flour, and lots of added sugar.monticelllo/Getty Images <ul><li>Fast food's recession playbook is breaking as deals fail to lure pressured consume\u2026 [+5286 chars]"
  ],
  "num_chunks": 1,
  "processed_at": "2026-02-07T11:42:03.586621"
}